odoo/addons/sale_last_price_info/README.rst
odoo/addons/sale_last_price_info/__init__.py
odoo/addons/sale_last_price_info/__manifest__.py
odoo/addons/sale_last_price_info/i18n/de.po
odoo/addons/sale_last_price_info/i18n/es.po
odoo/addons/sale_last_price_info/i18n/fr.po
odoo/addons/sale_last_price_info/i18n/it.po
odoo/addons/sale_last_price_info/i18n/sale_last_price_info.pot
odoo/addons/sale_last_price_info/i18n/sl_SI.po
odoo/addons/sale_last_price_info/i18n/zh_CN.po
odoo/addons/sale_last_price_info/models/__init__.py
odoo/addons/sale_last_price_info/models/product.py
odoo/addons/sale_last_price_info/models/sale.py
odoo/addons/sale_last_price_info/readme/CONTRIBUTORS.rst
odoo/addons/sale_last_price_info/readme/DESCRIPTION.rst
odoo/addons/sale_last_price_info/static/description/icon.png
odoo/addons/sale_last_price_info/static/description/index.html
odoo/addons/sale_last_price_info/tests/__init__.py
odoo/addons/sale_last_price_info/tests/test_sale_last_price_info.py
odoo/addons/sale_last_price_info/views/product_view.xml
odoo13_addon_sale_last_price_info-13.0.1.0.1.dev12.dist-info/METADATA
odoo13_addon_sale_last_price_info-13.0.1.0.1.dev12.dist-info/WHEEL
odoo13_addon_sale_last_price_info-13.0.1.0.1.dev12.dist-info/top_level.txt
odoo13_addon_sale_last_price_info-13.0.1.0.1.dev12.dist-info/RECORD
